{"priorities":[{"id":"019408d6-7f2d-75d7-8853-5018a79edd93","body":"Hook up to proper db","order":1,"createdAt":"2024-12-27T15:57:42.573Z"},{"id":"01940870-0603-7738-a86f-bae9b69f454d","body":"Finish adding all the required features to release this app into the wild!","order":2,"createdAt":"2024-12-27T14:05:46.883Z"},{"id":"0194129e-d300-74be-a41d-0d0d60a8a2a7","body":"Add animations when doing stuff (adding, removing, completing todos, etc.)","order":3,"createdAt":"2024-12-29T13:33:06.176Z"},{"id":"019412de-cee1-7669-8818-53d497964266","body":"Add a command interface because why not","order":4,"createdAt":"2024-12-29T14:42:59.425Z"},{"id":"019412e9-771d-7172-9bc0-7a78d9695210","body":"Add shortcuts for stuff like search etc.","order":5,"createdAt":"2024-12-29T14:54:37.853Z"},{"id":"019408d4-234b-776f-8406-d77d31d13e2b","body":"Add warning dialog before deleting shit (DONE)","order":6,"createdAt":"2024-12-27T15:55:07.979Z"},{"id":"0194129f-0ffe-761b-95b6-843a2c21e69f","body":"Allow archiving / completing todos (DONE)","order":7,"createdAt":"2024-12-29T13:33:21.790Z"},{"id":"019408d4-b95b-77fc-a748-9f0d5e6e4c84","body":"Drag 'n Drop priorities (DONE)","order":8,"createdAt":"2024-12-27T15:55:46.395Z"}]}